indo_arabic_transliteration/__init__.py
indo_arabic_transliteration/__version.py
indo_arabic_transliteration/base.py
indo_arabic_transliteration/common.py
indo_arabic_transliteration/hindustani.py
indo_arabic_transliteration/lossless_converter.py
indo_arabic_transliteration/mapper.py
indo_arabic_transliteration/ml_based.py
indo_arabic_transliteration/punjabi.py
indo_arabic_transliteration/sangam_api.py
indo_arabic_transliteration/script_converter.py
indo_arabic_transliteration/sindhi.py
indo_arabic_transliteration/str_mapper.py
indo_arabic_transliteration/utils.py
indo_arabic_transliteration/data/arabic.csv
indo_arabic_transliteration/data/final_vowels.csv
indo_arabic_transliteration/data/hamza.csv
indo_arabic_transliteration/data/hamza_combo.csv
indo_arabic_transliteration/data/hindustani_consonants.csv
indo_arabic_transliteration/data/initial_vowels.csv
indo_arabic_transliteration/data/numerals.csv
indo_arabic_transliteration/data/punctuations.csv
indo_arabic_transliteration/data/sindhi_consonants.csv
indo_arabic_transliteration/data/sindhi_final.csv
indo_arabic_transliteration/data/sindhi_final_consonants.csv
indo_arabic_transliteration/data/sindhi_isolated.csv
indo_arabic_transliteration/data/vowels.csv
indo_arabic_transliteration-0.1.5.dist-info/METADATA
indo_arabic_transliteration-0.1.5.dist-info/WHEEL
indo_arabic_transliteration-0.1.5.dist-info/top_level.txt
indo_arabic_transliteration-0.1.5.dist-info/RECORD
