Metadata-Version: 2.1
Name: indo-arabic-transliteration
Version: 0.1.5
Summary: Script Conversion for Indo-Pakistani languages
Home-page: https://github.com/GokulNC/Indic-PersoArabic-Script-Converter
Author: Gokul NC
License: UNKNOWN
Platform: UNKNOWN
Classifier: Programming Language :: Python :: 3
Classifier: Operating System :: OS Independent
Classifier: Topic :: Scientific/Engineering :: Artificial Intelligence
Classifier: Topic :: Software Development :: Libraries
Requires-Dist: pandas
Requires-Dist: urduhack
Requires-Dist: aksharamukha
